termnote/__init__.py
termnote/termnote.py
termnote-1.0.2.data/scripts/termnote
termnote-1.0.2.data/scripts/tn
termnote-1.0.2.dist-info/DESCRIPTION.rst
termnote-1.0.2.dist-info/METADATA
termnote-1.0.2.dist-info/RECORD
termnote-1.0.2.dist-info/WHEEL
termnote-1.0.2.dist-info/metadata.json
termnote-1.0.2.dist-info/top_level.txt
