Metadata-Version: 2.0
Name: termnote
Version: 1.0.2
Summary: A simple, yet powerful and handy terminal based note taking python app
Home-page: https://github.com/sayanarijit/termnote
Author: Arijit Basu
Author-email: sayanarijit@gmail.com
License: UNKNOWN
Download-URL: https://github.com/sayanarijit/termnote/archive/v1.0.2.tar.gz
Keywords: Notes Management Terminal App
Platform: UNKNOWN
Classifier: Environment :: Console
Classifier: Development Status :: 5 - Production/Stable
Classifier: Intended Audience :: Developers
Classifier: Intended Audience :: Information Technology
Classifier: Intended Audience :: System Administrators
Classifier: License :: OSI Approved :: MIT License
Classifier: Natural Language :: English
Classifier: Programming Language :: Python
Classifier: Topic :: Utilities
Classifier: Operating System :: MacOS
Classifier: Operating System :: POSIX
Requires-Dist: prompt-toolkit (==1.0.15)
